{
	"parentTaskName": "bundle",
	"concat": {
		"active": true,
		"config": {}
	},
	"uglify": {
		"active": false,
		"config": {}
	},
	"sourcemap": {
		"active": true,
		"config": {}
	},
	"destinationFolder": "dist",
	"files": {
		"js/main-bundle.js": [
			"dist/js/main.js"
		],
		"js/controllers.js": [
			"dist/js/controllers/CPost.js",
			"dist/js/controllers/CBlog.js",
			"dist/js/controllers/CAddPost.js"
		],
		"js/factories.js": [
			"dist/js/factories/FApi.js",
			"dist/js/factories/FPost.js"
		],
		"css/main-bundle.css": [
			"dist/css/main.css"
		]
	}
}
